iotamine/__init__.py
iotamine/client.py
iotamine/core.py
iotamine/exceptions.py
iotamine/vm.py
iotamine-0.1.1.dist-info/METADATA
iotamine-0.1.1.dist-info/WHEEL
iotamine-0.1.1.dist-info/top_level.txt
iotamine-0.1.1.dist-info/RECORD
