Metadata-Version: 2.4
Name: iotamine
Version: 0.1.1
Summary: Iotamine Cloud API Python SDK
Home-page: https://github.com/piyushladhar/iotamine
Author: Piyush Ladhar
Author-email: corporate@iotamine.com
Project-URL: Documentation, https://github.com/piyushladhar/iotamine
Project-URL: Source, https://github.com/piyushladhar/iotamine
Classifier: Programming Language :: Python :: 3
Classifier: License :: OSI Approved :: MIT License
Classifier: Operating System :: OS Independent
Requires-Python: >=3.6
Requires-Dist: requests
Dynamic: author
Dynamic: author-email
Dynamic: classifier
Dynamic: description
Dynamic: description-content-type
Dynamic: home-page
Dynamic: project-url
Dynamic: requires-dist
Dynamic: requires-python
Dynamic: summary
